{"location":"Manila, Philippines","id":4390,"title":"Chief of Mission, Republic of the Philippines","expires":"","branch":"Executive","tenure":"","agcy_name":"Department of State","org_name":"Office of the Under Secretary for Political Affairs","pborg_seq":"5503","pborg_managed_by":"5487","org_order":"290","name_of_incumbent":"Harry K. Thomas, Jr.","type_of_appt":"Presidential Appointment with Senate Confirmation(PAS)","pay_plan":"Foreign Service Chiefs of Mission(FA)","pay":"","pb_order":"975"}