{"location":"Arlington, VA","id":891,"title":"Deputy Assistant Secretary of Defense for Senate Affairs","expires":"","branch":"Executive","tenure":"","agcy_name":"Department of Defense - Office of the Secretary of Defense","org_name":"Office of Assistant Secretary of Defense (Legislative Affairs)","pborg_seq":"5006","pborg_managed_by":"5022","org_order":"110","name_of_incumbent":"Michael John Stella","type_of_appt":"Noncareer Appointment(NA)","pay_plan":"Senior Executive Service(ES)","pay":"","pb_order":"15"}